fastami/__init__.py
fastami/fastami.py
fastami/fastsmi.py
fastami/utils.py
fastami-0.2.1.dist-info/LICENSE
fastami-0.2.1.dist-info/METADATA
fastami-0.2.1.dist-info/WHEEL
fastami-0.2.1.dist-info/RECORD
